guillotina_dynamictablestorage/__init__.py
guillotina_dynamictablestorage/tests/__init__.py
guillotina_dynamictablestorage/tests/conftest.py
guillotina_dynamictablestorage/tests/fixtures.py
guillotina_dynamictablestorage/tests/test_storages.py
guillotina_dynamictablestorage-1.1.1.dist-info/METADATA
guillotina_dynamictablestorage-1.1.1.dist-info/WHEEL
guillotina_dynamictablestorage-1.1.1.dist-info/top_level.txt
guillotina_dynamictablestorage-1.1.1.dist-info/RECORD
